fedimpute/__init__.py
fedimpute/data_prep/__init__.py
fedimpute/data_prep/data_prep.py
fedimpute/data_prep/helper.py
fedimpute/data_prep/load_data.py
fedimpute/evaluation/__init__.py
fedimpute/evaluation/evaluator.py
fedimpute/evaluation/fed_prediction/__init__.py
fedimpute/evaluation/fed_prediction/fed_pred_lr.py
fedimpute/evaluation/fed_prediction/fed_pred_rf.py
fedimpute/evaluation/fed_prediction/fed_pred_sklnn.py
fedimpute/evaluation/fed_prediction/fed_pred_svm.py
fedimpute/evaluation/fed_prediction/fed_pred_torchnn.py
fedimpute/evaluation/fed_prediction/fed_pred_xgboost.py
fedimpute/evaluation/fed_regression_analysis/__init__.py
fedimpute/evaluation/fed_regression_analysis/linear.py
fedimpute/evaluation/fed_regression_analysis/logit.py
fedimpute/evaluation/fed_regression_analysis/mnlogit.py
fedimpute/evaluation/imp_quality_metrics.py
fedimpute/evaluation/pred_model_metrics.py
fedimpute/evaluation/tsne.py
fedimpute/evaluation/twonn.py
fedimpute/execution_environment/__init__.py
fedimpute/execution_environment/client/__init__.py
fedimpute/execution_environment/client/client.py
fedimpute/execution_environment/client/utils.py
fedimpute/execution_environment/env_fedimp.py
fedimpute/execution_environment/fed_strategy/__init__.py
fedimpute/execution_environment/fed_strategy/fed_strategy_client/__init__.py
fedimpute/execution_environment/fed_strategy/fed_strategy_client/basic_strategy.py
fedimpute/execution_environment/fed_strategy/fed_strategy_client/fedavg.py
fedimpute/execution_environment/fed_strategy/fed_strategy_client/fednova.py
fedimpute/execution_environment/fed_strategy/fed_strategy_client/fedopt.py
fedimpute/execution_environment/fed_strategy/fed_strategy_client/fedprox.py
fedimpute/execution_environment/fed_strategy/fed_strategy_client/local_nn.py
fedimpute/execution_environment/fed_strategy/fed_strategy_client/scaffold.py
fedimpute/execution_environment/fed_strategy/fed_strategy_client/strategy_base.py
fedimpute-0.2.3.dist-info/LICENSE
fedimpute-0.2.3.dist-info/METADATA
fedimpute-0.2.3.dist-info/WHEEL
fedimpute-0.2.3.dist-info/RECORD
