Metadata-Version: 2.3
Name: fedimpute
Version: 0.2.3
Summary: fedimpute is a benchmarking tool for federated imputation
License: GPL GNU v3.0
Author: Sitao Min (idlsa Rutgers University)
Author-email: sitaomin1994@gmail.com
Requires-Python: >=3.12.3,<4.0.0
Classifier: License :: Other/Proprietary License
Classifier: Programming Language :: Python :: 3
Classifier: Programming Language :: Python :: 3.13
Requires-Dist: gower (==0.1.2)
Requires-Dist: loguru (==0.7.3)
Requires-Dist: matplotlib (==3.10.1)
Requires-Dist: n-sphere (==1.2.0)
Requires-Dist: numpy (==1.26.4)
Requires-Dist: openpyxl (==3.1.5)
Requires-Dist: pandas (==2.2.2)
Requires-Dist: pot (==0.9.5)
Requires-Dist: requests (==2.32.3)
Requires-Dist: scikit-learn (==1.6.1)
Requires-Dist: seaborn (==0.13.2)
Requires-Dist: statsmodels (==0.14.4)
Requires-Dist: tabulate (==0.9.0)
Requires-Dist: tensorboard (==2.19.0)
Requires-Dist: tqdm (==4.67.1)
Requires-Dist: xgboost (==3.0.0)
